{
	"configurations" : 
	[
		{
			"directories" : 
			[
				{
					"build" : ".",
					"minimumCMakeVersion" : 
					{
						"string" : "3.6.0"
					},
					"projectIndex" : 0,
					"source" : "."
				}
			],
			"name" : "Debug",
			"projects" : 
			[
				{
					"directoryIndexes" : 
					[
						0
					],
					"name" : "Project"
				}
			],
			"targets" : []
		}
	],
	"kind" : "codemodel",
	"paths" : 
	{
		"build" : "/home/rdemont/Projects/dev/git/Trees-Marking/android/app/.cxx/Debug/3f322d1i/x86_64",
		"source" : "/home/rdemont/Android/flutter/packages/flutter_tools/gradle/src/main/groovy"
	},
	"version" : 
	{
		"major" : 2,
		"minor" : 1
	}
}
